__init__.py
xisf.py
xisf-0.9.5.dist-info/LICENSE
xisf-0.9.5.dist-info/METADATA
xisf-0.9.5.dist-info/WHEEL
xisf-0.9.5.dist-info/top_level.txt
xisf-0.9.5.dist-info/RECORD
