Metadata-Version: 2.1
Name: xisf
Version: 0.9.5
Summary: Encoder/Decoder for XISF (Extensible Image Serialization Format)
Author-email: Sergio Díaz <sergio.diaz.ruiz@gmail.com>
License: GNU General Public License v3 (GPLv3)
Project-URL: Homepage, https://github.com/sergio-dr/xisf
Keywords: astronomy,XISF
Classifier: License :: OSI Approved :: GNU General Public License v3 (GPLv3)
Classifier: Operating System :: OS Independent
Classifier: Programming Language :: Python :: 3
Classifier: Topic :: Scientific/Engineering :: Astronomy
Classifier: Topic :: Scientific/Engineering :: Image Processing
Requires-Python: >=3.6
License-File: LICENSE
Requires-Dist: numpy
Requires-Dist: lz4
Requires-Dist: zstandard
